ciervo/__init__.py
ciervo/parameters.py
ciervo/aux_tools/__init__.py
ciervo/aux_tools/buffer.py
ciervo/aux_tools/devices.py
ciervo/aux_tools/fix_bioradio_csv.py
ciervo/io/__init__.py
ciervo/io/load.py
ciervo/io/store_stream.py
ciervo/io/stream.py
ciervo/models/__init__.py
ciervo/models/estirar.py
ciervo/models/features.py
ciervo/models/label.py
ciervo/models/predict.py
ciervo/models/realtime_inference.py
ciervo/models/split.py
ciervo/models/train.py
ciervo/models/dataset/__init__.py
ciervo/models/dataset/dataset.py
ciervo/models/redes/__init__.py
ciervo/models/redes/rnn.py
ciervo/plots/__init__.py
ciervo/plots/emg.py
ciervo/plots/stream_plot.py
ciervo/procesamiento/__init__.py
ciervo/procesamiento/filtrado.py
ciervo/simulation/__init__.py
ciervo/simulation/synthetic_stream.py
ciervo/tests/__init__.py
ciervo-2024.10.30.dist-info/METADATA
ciervo-2024.10.30.dist-info/WHEEL
ciervo-2024.10.30.dist-info/top_level.txt
ciervo-2024.10.30.dist-info/RECORD
