Metadata-Version: 2.1
Name: ciervo
Version: 2024.10.30
Summary: Ciervo for prosthetic leg control
Author: Carlos Valle
Author-email: cgvallea@gmail.com
Keywords: python,first package
Classifier: Development Status :: 3 - Alpha
Classifier: Intended Audience :: Education
Classifier: Programming Language :: Python :: 3
Classifier: Operating System :: MacOS :: MacOS X
Classifier: Operating System :: Microsoft :: Windows
Classifier: Operating System :: POSIX :: Linux
